{
 "run_id": "run_20260801_BTC_q1",
 "generated_at": "2026-08-01T02:40:00Z",
 "passed": true,
 "checks": [
  "completeness",
  "allowed_values",
  "timestamp_format",
  "interpretation_number_traceability",
  "reference_existence",
  "hierarchy_rules",
  "statement_number_traceability",
  "conflict_coverage"
 ],
 "stats": {
  "evidence_count": 10,
  "evidence_by_category": {
   "price_technical": 3,
   "onchain": 2,
   "news": 2,
   "sentiment": 2,
   "macro": 1
  },
  "evidence_by_tier": {
   "tier0_official": 6,
   "tier2_aggregator": 2,
   "tier1_major_media": 1,
   "tier3_community": 1
  },
  "independence_groups": 10,
  "claim_count": 5,
  "claims_by_type": {
   "fact": 3,
   "inference": 1,
   "conclusion": 1
  },
  "conflict_count": 1,
  "conflicts_resolved": 1
 },
 "error_count": 0,
 "errors": []
}